cliz/__init__.py
cliz/main.py
cliz/shell.py
cliz-0.1.4.dist-info/licenses/LICENSE
cliz-0.1.4.dist-info/METADATA
cliz-0.1.4.dist-info/WHEEL
cliz-0.1.4.dist-info/entry_points.txt
cliz-0.1.4.dist-info/top_level.txt
cliz-0.1.4.dist-info/RECORD
