Metadata-Version: 2.4
Name: cliz
Version: 0.1.4
Summary: A useful command-line agent help you work with your favorite tools
Author-email: lucario <xgzlucario@foxmail.com>
License-Expression: MIT
Requires-Python: >=3.11
License-File: LICENSE
Requires-Dist: agno==1.4.3
Requires-Dist: html2text>=2025.4.15
Requires-Dist: openai>=1.76.2
Requires-Dist: sqlalchemy>=2.0.40
Dynamic: license-file
